jiosaavnapi/__init__.py
jiosaavnapi/endpoints.py
jiosaavnapi/functions.py
jiosaavnapi/jiosaavn.py
jiosaavnapi-0.0.1.dist-info/METADATA
jiosaavnapi-0.0.1.dist-info/WHEEL
jiosaavnapi-0.0.1.dist-info/top_level.txt
jiosaavnapi-0.0.1.dist-info/RECORD
